atomate2/turbomole/__init__.py
atomate2/turbomole/_version.py
atomate2/turbomole/utils.py
atomate2/turbomole/custodian/__init__.py
atomate2/turbomole/custodian/jobs.py
atomate2/turbomole/custodian/validators.py
atomate2/turbomole/flows/__init__.py
atomate2/turbomole/flows/core.py
atomate2/turbomole/jobs/__init__.py
atomate2/turbomole/jobs/base.py
atomate2/turbomole/jobs/core.py
atomate2/turbomole/schemas/__init__.py
atomate2/turbomole/schemas/calculation.py
atomate2/turbomole/schemas/task.py
atomate2/turbomole/schemas/calc_types/__init__.py
atomate2/turbomole/sets/__init__.py
atomate2/turbomole/sets/base.py
atomate2/turbomole/sets/core.py
atomate2_turbomole-0.3.dist-info/LICENSE
atomate2_turbomole-0.3.dist-info/METADATA
atomate2_turbomole-0.3.dist-info/WHEEL
atomate2_turbomole-0.3.dist-info/top_level.txt
atomate2_turbomole-0.3.dist-info/RECORD
